{"title":"JQurey对象和DOM对象实例操作（笔记）","slug":"5","date":"2018-11-07T05:39:20.547Z","updated":"2018-11-07T06:04:36.108Z","comments":true,"path":"api/articles/5.json","photos":[],"link":"","excerpt":null,"covers":null,"content":"<blockquote><p>JQuery 对象无法使用DOM对象的任何方法 例如$(“#id”).innerHTML和$(“#id”).checked 之类的写法都是错的<br>但是可以用$(“#id”).html()和$(“#id”).attr(“checked”)之类的JQuery方法来代替<br>JQuery 提供了两种方法将一个JQuery对象转化为DOM对象，即[index]和 get（index）;</p>\n</blockquote>\n<figure class=\"highlight livecodeserver\"><table><tr><td class=\"gutter\"><pre><span class=\"line\">1</span><br><span class=\"line\">2</span><br><span class=\"line\">3</span><br><span class=\"line\">4</span><br></pre></td><td class=\"code\"><pre><span class=\"line\"> var $<span class=\"literal\">cr</span> = $(<span class=\"string\">\"#cr\"</span>);\t<span class=\"comment\">\t//JQuery对象</span></span><br><span class=\"line\"> var  <span class=\"literal\">cr</span> =$<span class=\"literal\">cr</span>[<span class=\"number\">0</span>];\t\t<span class=\"comment\">\t//DOM对象</span></span><br><span class=\"line\">alert(<span class=\"literal\">cr</span>.checked);\t\t<span class=\"comment\">\t//检测这个CheckBox是否被选中</span></span><br><span class=\"line\"></span><br></pre></td></tr></table></figure>\n<figure class=\"highlight livecodeserver\"><table><tr><td class=\"gutter\"><pre><span class=\"line\">1</span><br><span class=\"line\">2</span><br><span class=\"line\">3</span><br><span class=\"line\">4</span><br><span class=\"line\">5</span><br></pre></td><td class=\"code\"><pre><span class=\"line\"></span><br><span class=\"line\"> var $<span class=\"literal\">cr</span> = $(<span class=\"string\">\"#cr\"</span>);\t<span class=\"comment\">\t//JQuery对象</span></span><br><span class=\"line\"> var  <span class=\"literal\">cr</span> =<span class=\"literal\">cr</span>.<span class=\"built_in\">get</span>(<span class=\"number\">0</span>);\t\t<span class=\"comment\">\t//DOM对象</span></span><br><span class=\"line\">alert(<span class=\"literal\">cr</span>.checked);\t\t<span class=\"comment\">\t//检测这个CheckBox是否被选中</span></span><br><span class=\"line\"></span><br></pre></td></tr></table></figure>\n<blockquote><p>对于一个DOM对象， 只需要用$()把DOM对象给包装起来，就可以获得一个JQuery对象了<br>方式为$(DOM对象) 代码如下</p>\n</blockquote>\n<figure class=\"highlight javascript\"><table><tr><td class=\"gutter\"><pre><span class=\"line\">1</span><br><span class=\"line\">2</span><br></pre></td><td class=\"code\"><pre><span class=\"line\"><span class=\"keyword\">var</span> cr=<span class=\"built_in\">document</span>.getElementById(<span class=\"string\">\"cr\"</span>);\t\t\t<span class=\"comment\">//DOM对象</span></span><br><span class=\"line\"><span class=\"keyword\">var</span> $cr=$(cr);\t\t\t\t\t\t\t\t\t<span class=\"comment\">//JQuery对象</span></span><br></pre></td></tr></table></figure>","categories":[{"name":"JavaScript","slug":"JavaScript","count":3,"path":"api/categories/JavaScript.json"},{"name":"JQuery","slug":"JavaScript/JQuery","count":3,"path":"api/categories/JavaScript/JQuery.json"}],"tags":[{"name":"笔记","slug":"笔记","count":5,"path":"api/tags/笔记.json"},{"name":"JQuery","slug":"JQuery","count":2,"path":"api/tags/JQuery.json"}]}